fund_investment_calculator-0.1.0.dist-info/licenses/LICENSE
src/__init__.py
src/fund.py
src/nav_provider.py
src/scheduler.py
src/trading_calendar.py
fund_investment_calculator-0.1.0.dist-info/METADATA
fund_investment_calculator-0.1.0.dist-info/WHEEL
fund_investment_calculator-0.1.0.dist-info/top_level.txt
fund_investment_calculator-0.1.0.dist-info/RECORD
