Metadata-Version: 2.4
Name: fund-investment-calculator
Version: 0.1.0
Summary: 基金定投收益计算工具，支持自动获取净值数据和交易日判断
Author-email: liwenyi <lwy.lwy@163.com>
License: MIT
Project-URL: Homepage, https://github.com/wenyili/fund-investment-calculator
Project-URL: Repository, https://github.com/wenyili/fund-investment-calculator
Project-URL: Bug Tracker, https://github.com/wenyili/fund-investment-calculator/issues
Keywords: fund,investment,financial,calculator,定投
Classifier: Development Status :: 3 - Alpha
Classifier: Intended Audience :: Developers
Classifier: Intended Audience :: Financial and Insurance Industry
Classifier: License :: OSI Approved :: MIT License
Classifier: Programming Language :: Python :: 3
Classifier: Programming Language :: Python :: 3.9
Classifier: Programming Language :: Python :: 3.10
Classifier: Programming Language :: Python :: 3.11
Classifier: Programming Language :: Python :: 3.12
Classifier: Programming Language :: Python :: 3.13
Classifier: Topic :: Office/Business :: Financial :: Investment
Requires-Python: >=3.9
License-File: LICENSE
Requires-Dist: akshare>=1.14.0
Requires-Dist: exchange-calendars>=4.5.0
Requires-Dist: pandas>=2.0.0
Requires-Dist: scipy>=1.11.0
Provides-Extra: dev
Requires-Dist: pytest>=7.0.0; extra == "dev"
Requires-Dist: pytest-cov>=4.0.0; extra == "dev"
Dynamic: license-file
